ascript/__init__.py
ascript/android/__init__.py
ascript/android/cloud_control.py
ascript/android/data.py
ascript/android/media.py
ascript/android/node.py
ascript/android/plug.py
ascript/android/ui.py
ascript/android/action/__init__.py
ascript/android/action/ashid.py
ascript/android/screen/__init__.py
ascript/android/screen/ascv.py
ascript/android/screen/color_tools.py
ascript/android/screen/gp.py
ascript/android/screen/gp_tasks.py
ascript/android/screen/gp_tool.py
ascript/android/shizuku/__init__.py
ascript/android/system/__init__.py
ascript/hooks/__init__.py
ascript/hooks/hook-ascript.py
ascript/ios/__init__.py
ascript/ios/ime.py
ascript/ios/media.py
ascript/ios/node.py
ascript/ios/ui.py
ascript/ios/action/__init__.py
ascript/ios/developer/__init__.py
ascript/ios/developer/ws.py
ascript/ios/developer/api/__init__.py
ascript/ios/developer/api/api_2_android.py
ascript/ios/developer/api/api_code.py
ascript/ios/developer/api/api_file.py
ascript/ios/developer/api/api_label.py
ascript/ios/developer/api/api_module.py
ascript/ios/developer/api/api_node.py
ascript/ios/developer/api/api_screen.py
ascript/ios/developer/api/api_tool.py
ascript/ios/developer/api/dao.py
ascript/ios/developer/api/data.py
ascript/ios/developer/api/file_utils.py
ascript/ios/developer/api/label_utils.py
ascript/ios/developer/api/line_helper.py
ascript/ios/developer/api/oc.py
ascript/ios/developer/api/oc_gp.py
ascript/ios/developer/api/sp_utils.py
ascript/ios/developer/api/utils.py
ascript/ios/developer/api/wda_gp.py
ascript/ios/screen/__init__.py
ascript/ios/screen/ascv.py
ascript/ios/screen/color_tools.py
ascript/ios/screen/dao.py
ascript/ios/screen/gp.py
ascript/ios/screen/yolov8.py
ascript/ios/system/__init__.py
ascript/ios/system/device.py
ascript/ios/wdapy/__init__.py
ascript/ios/wdapy/_alert.py
ascript/ios/wdapy/_base.py
ascript/ios/wdapy/_node.py
ascript/ios/wdapy/_proto.py
ascript/ios/wdapy/_types.py
ascript/ios/wdapy/_utils.py
ascript/ios/wdapy/_wdapy.py
ascript/ios/wdapy/_wrap.py
ascript-1.2.5.dist-info/METADATA
ascript-1.2.5.dist-info/WHEEL
ascript-1.2.5.dist-info/top_level.txt
ascript-1.2.5.dist-info/RECORD
