Metadata-Version: 2.4
Name: ascript
Version: 1.2.5
Summary: Ascript Developer Library
License: MIT
Classifier: Operating System :: Microsoft :: Windows
Classifier: Programming Language :: Python :: 3
Classifier: Programming Language :: Python :: 3.9
Classifier: Programming Language :: Python :: 3.10
Classifier: Programming Language :: Python :: 3.11
Classifier: Programming Language :: Python :: 3.12
Classifier: Programming Language :: Python :: 3.13
Classifier: License :: OSI Approved :: MIT License
Classifier: Development Status :: 4 - Beta
Classifier: Intended Audience :: Developers
Classifier: Topic :: Software Development :: Libraries :: Python Modules
Requires-Python: >=3.9
Requires-Dist: pkginfo>=1.10.0
Requires-Dist: eel>=0.17.0
Requires-Dist: pystray>=0.19.5
Requires-Dist: pywebview>=5.0
Requires-Dist: gevent>=23.9.1
Requires-Dist: bottle>=0.12.25
Requires-Dist: bottle-websocket>=0.2.9
Requires-Dist: uiautomation>=2.0.20
Requires-Dist: pywin32>=306
Requires-Dist: psutil>=5.9.0
Requires-Dist: pyautogui>=0.9.54
Requires-Dist: opencv-python>=4.9.0.0
Requires-Dist: pillow>=10.0.0
Requires-Dist: numpy>=1.26.0
Requires-Dist: mss>=9.0.1
Requires-Dist: pycryptodome>=3.20.0
Requires-Dist: requests>=2.28.0
Provides-Extra: dev
Requires-Dist: pyinstaller>=6.0.0; extra == "dev"
